hookflow/__init__.py
hookflow/__main__.py
hookflow/main.py
hookflow/bin/hookflow-darwin-arm64/hookflow
hookflow/bin/hookflow-darwin-x86_64/hookflow
hookflow/bin/hookflow-freebsd-arm64/hookflow
hookflow/bin/hookflow-freebsd-x86_64/hookflow
hookflow/bin/hookflow-linux-arm64/hookflow
hookflow/bin/hookflow-linux-x86_64/hookflow
hookflow/bin/hookflow-openbsd-arm64/hookflow
hookflow/bin/hookflow-openbsd-x86_64/hookflow
hookflow/bin/hookflow-windows-arm64/hookflow.exe
hookflow/bin/hookflow-windows-x86_64/hookflow.exe
hookflow-1.0.0.dist-info/licenses/LICENSE
hookflow-1.0.0.dist-info/METADATA
hookflow-1.0.0.dist-info/WHEEL
hookflow-1.0.0.dist-info/entry_points.txt
hookflow-1.0.0.dist-info/top_level.txt
hookflow-1.0.0.dist-info/RECORD
