Metadata-Version: 2.4
Name: hookflow
Version: 1.0.0
Summary: Git hooks manager. Fast, powerful, simple.
Home-page: https://github.com/tekintian/hookflow
Author: Tekintian
Author-email: tekintian@gmail.com
Classifier: License :: OSI Approved :: MIT License
Classifier: Operating System :: OS Independent
Classifier: Topic :: Software Development :: Version Control :: Git
Requires-Python: >=3.6
License-File: LICENSE
Dynamic: author
Dynamic: author-email
Dynamic: classifier
Dynamic: description
Dynamic: description-content-type
Dynamic: home-page
Dynamic: license-file
Dynamic: requires-python
Dynamic: summary
